README.rst
setup.cfg
setup.py
niceconf/__init__.py
niceconf/source.py
niceconf.egg-info/PKG-INFO
niceconf.egg-info/SOURCES.txt
niceconf.egg-info/dependency_links.txt
niceconf.egg-info/top_level.txt