Metadata-Version: 1.1
Name: niceconf
Version: 0.1.2
Summary: A nice config package
Home-page: https://github.com/tdb-alcorn/niceconf
Author: Thomas Alcorn
Author-email: tdb.alcorn@gmail.com
License: MIT
Download-URL: https://github.com/tdb-alcorn/niceconf/tarball/0.1.2
Keywords: config configuration
Platform: UNKNOWN
Classifier: Development Status :: 3 - Alpha
Classifier: Intended Audience :: Developers
Classifier: Intended Audience :: Science/Research
Classifier: Intended Audience :: System Administrators
Classifier: Topic :: System
Classifier: Topic :: Utilities
Classifier: License :: OSI Approved :: MIT License
Classifier: Programming Language :: Python :: 2
Classifier: Programming Language :: Python :: 2.6
Classifier: Programming Language :: Python :: 2.7
